init.py
usb_wire-1.0.2.dist-info/METADATA
usb_wire-1.0.2.dist-info/WHEEL
usb_wire-1.0.2.dist-info/top_level.txt
usb_wire-1.0.2.dist-info/RECORD
